dayan_contextcapture/Analyze.py
dayan_contextcapture/__init__.py
dayan_contextcapture/analyze_contextcapture.py
dayan_contextcapture/constants.py
dayan_contextcapture/tests/__init__.py
dayan_contextcapture/tests/conftest.py
dayan_contextcapture/tests/test_analyze.py
dayan_contextcapture-1.0.2.dist-info/LICENSE
dayan_contextcapture-1.0.2.dist-info/METADATA
dayan_contextcapture-1.0.2.dist-info/WHEEL
dayan_contextcapture-1.0.2.dist-info/top_level.txt
dayan_contextcapture-1.0.2.dist-info/RECORD
