Metadata-Version: 2.1
Name: dayan-contextcapture
Version: 1.0.2
Summary: A Python-based API for Using Dayan cloud rendering service.
Home-page: https://gitlab.renderbus.com/internal/dayan_contextcapture
Author: Shenzhen Rayvision Technology Co., Ltd
Author-email: developer@rayvision.com
License: UNKNOWN
Platform: UNKNOWN
Classifier: Programming Language :: Python
Classifier: Programming Language :: Python :: 3
Requires-Dist: attrs (==19.3.0)
Requires-Dist: cattrs (==1.0.0)
Requires-Dist: tenacity (==6.0.0)
Requires-Dist: future (==0.18.2)
Requires-Dist: requests (==2.23.0)
Requires-Dist: Cerberus (==1.1.0)
Requires-Dist: rayvision-utils (==1.2.1)
Requires-Dist: dayan-api (>=1.6)
Requires-Dist: dayan-sync (>=1.0)
Requires-Dist: configparser (==4.0.2)
Requires-Dist: colorama (==0.4.5)
Requires-Dist: ExifRead (==3.0.0)
Requires-Dist: Pillow (==8.4.0)
Requires-Dist: tqdm (==4.64.0)
Requires-Dist: Pygments (==2.12.0)
Requires-Dist: rayvision-log (>=0.3.3)
